alquran_id/__init__.py
alquran_id/quran.py
alquran_id/source/quran.xml
alquran_id/source/tafsir.xml
alquran_id/source/terjemahan.xml
alquran_id-0.0.2.dist-info/LICENSE
alquran_id-0.0.2.dist-info/METADATA
alquran_id-0.0.2.dist-info/WHEEL
alquran_id-0.0.2.dist-info/top_level.txt
alquran_id-0.0.2.dist-info/RECORD
