Metadata-Version: 2.1
Name: alquran-id
Version: 0.0.2
Summary: Al-Quran, Terjemahan Indonesia dan Tafsir Jalalayn
Home-page: https://gitlab.com/nesstero/quran-id
Author: nestero
Author-email: nestero@mail.com
License: MIT
Platform: UNKNOWN
License-File: LICENSE
